{
      "session_file": "6283861149700",
      "phone": "6283861149700",
      "register_time": 1661986667,
      "app_id": "2040",
      "app_hash": "b18441a1ff607e10a989891a5462e627",
      "sdk": "Windows 8",
      "app_version": "3.7.3 x64",
      "device": "765802U",
      "last_check_time": 1661986667,
      "first_name": "Meagan",
      "last_name": "Frank",
      "lang_pack": "tdesktop",
      "system_lang_pack": "en-US",
      "lang_code": "en",
      "proxy": null,
      "ipv6": false,
      "username": null,
      "avatar": "img/default.png"
}